Metadata-Version: 2.1
Name: cthmm
Version: 0.0.2
Summary: Testing installation of Package
Home-page: https://github.com/field-cady/cthmm
Author: Field Cady
Author-email: field.cady@gmail.com
License: MIT
Platform: UNKNOWN
License-File: LICENSE
